guoguo_mcp/__init__.py
guoguo_mcp_server-1.0.0.dist-info/METADATA
guoguo_mcp_server-1.0.0.dist-info/WHEEL
guoguo_mcp_server-1.0.0.dist-info/entry_points.txt
guoguo_mcp_server-1.0.0.dist-info/licenses/LICENSE
guoguo_mcp_server-1.0.0.dist-info/RECORD
