Metadata-Version: 2.4
Name: guoguo-mcp-server
Version: 1.0.0
Summary: 寄件服务MCP Server - 提供寄件订单管理、地址簿查询等功能
Project-URL: Homepage, https://github.com/yourusername/guoguo-mcp
Project-URL: Bug Reports, https://github.com/yourusername/guoguo-mcp/issues
Project-URL: Source, https://github.com/yourusername/guoguo-mcp
Author-email: MCP Development Team <dev@example.com>
License: MIT
License-File: LICENSE
Keywords: logistics,mcp,server,shipping
Classifier: Development Status :: 4 - Beta
Classifier: Intended Audience :: Developers
Classifier: License :: OSI Approved :: MIT License
Classifier: Programming Language :: Python :: 3
Classifier: Programming Language :: Python :: 3.8
Classifier: Programming Language :: Python :: 3.9
Classifier: Programming Language :: Python :: 3.10
Classifier: Programming Language :: Python :: 3.11
Classifier: Programming Language :: Python :: 3.12
Classifier: Topic :: Communications
Classifier: Topic :: Software Development :: Libraries :: Python Modules
Requires-Python: >=3.8
Requires-Dist: fastapi>=0.104.0
Requires-Dist: mcp[cli]>=1.0.0
Requires-Dist: pydantic>=2.0.0
Requires-Dist: python-dotenv>=1.0.0
Requires-Dist: uvicorn>=0.32.1
